sinamet/__init__.py
sinamet/config.py
sinamet/errors.py
sinamet/mapper.py
sinamet/sidb.py
sinamet/mtobjects/__init__.py
sinamet/mtobjects/actor.py
sinamet/mtobjects/dbobject.py
sinamet/mtobjects/gateflow.py
sinamet/mtobjects/mtobject.py
sinamet/mtobjects/pathflow.py
sinamet/mtobjects/product.py
sinamet/mtobjects/property.py
sinamet/mtobjects/quantifiable.py
sinamet/mtobjects/stock.py
sinamet/mtobjects/territory.py
sinamet/tools/__init__.py
sinamet/tools/dataframe.py
sinamet/tools/dictsyntax.py
sinamet/tools/listmtq.py
sinamet/tools/opestring.py
sinamet/tools/path.py
sinamet/tools/profile.py
sinamet/tools/shell.py
sinamet/tools/timext.py
sinamet/tools/unitconverter.py
sinamet-0.1.2.dist-info/METADATA
sinamet-0.1.2.dist-info/WHEEL
sinamet-0.1.2.dist-info/licenses/LICENSE
sinamet-0.1.2.dist-info/RECORD
