Metadata-Version: 2.4
Name: sinamet
Version: 0.1.2
Summary: Structuring data to analyze territorial flows.
Project-URL: Documentation, https://docs.sinamet.tech
Project-URL: Source Code, https://gitlab.com/dynartio/sinamet
Author-email: Benoit Ribon <b.ribon@dynartio.com>, libadmin@sinamet.tech
License-Expression: MIT
License-File: LICENSE
Classifier: License :: OSI Approved :: MIT License
Classifier: Programming Language :: Python
Classifier: Programming Language :: Python :: 3.11
Classifier: Programming Language :: Python :: 3.12
Classifier: Programming Language :: Python :: 3.13
Requires-Python: >=3.11
Requires-Dist: anytree>=2.12.1
Requires-Dist: geoalchemy2>=0.16.0
Requires-Dist: numpy>=2.2.1
Requires-Dist: pandas>=2.2.3
Requires-Dist: psycopg2-binary>=2.9.10
Requires-Dist: shapely>=2.0.6
Requires-Dist: sqlalchemy>=2.0.36
Provides-Extra: demo
Requires-Dist: geopandas>=1.0.1; extra == 'demo'
Requires-Dist: openpyxl>=3.1.5; extra == 'demo'
Requires-Dist: xlrd>=2.0.1; extra == 'demo'
Provides-Extra: mkdocs
Requires-Dist: black; extra == 'mkdocs'
Requires-Dist: mkdocs; extra == 'mkdocs'
Requires-Dist: mkdocs-material; extra == 'mkdocs'
Requires-Dist: mkdocstrings[python]; extra == 'mkdocs'
